{
    "action": "created",
    "comment": {
      "author_association": "COLLABORATOR",
      "body": "/e2e",
      "created_at": "2019-11-14T14:21:14Z",
      "html_url": "https://github.com/store2be/E2E/pull/18#issuecomment-553908809",
      "id": 553908809,
      "issue_url": "https://api.github.com/repos/store2be/E2E/issues/18",
      "node_id": "MDEyOklzc3VlQ29tbWVudDU1MzkwODgwOQ==",
      "updated_at": "2019-11-14T14:21:14Z",
      "url": "https://api.github.com/repos/store2be/E2E/issues/comments/553908809",
      "user": {
        "avatar_url": "https://avatars1.githubusercontent.com/u/4454052?v=4",
        "events_url": "https://api.github.com/users/peterfication/events{/privacy}",
        "followers_url": "https://api.github.com/users/peterfication/followers",
        "following_url": "https://api.github.com/users/peterfication/following{/other_user}",
        "gists_url": "https://api.github.com/users/peterfication/gists{/gist_id}",
        "gravatar_id": "",
        "html_url": "https://github.com/peterfication",
        "id": 4454052,
        "login": "peterfication",
        "node_id": "MDQ6VXNlcjQ0NTQwNTI=",
        "organizations_url": "https://api.github.com/users/peterfication/orgs",
        "received_events_url": "https://api.github.com/users/peterfication/received_events",
        "repos_url": "https://api.github.com/users/peterfication/repos",
        "site_admin": false,
        "starred_url": "https://api.github.com/users/peterfication/starred{/owner}{/repo}",
        "subscriptions_url": "https://api.github.com/users/peterfication/subscriptions",
        "type": "User",
        "url": "https://api.github.com/users/peterfication"
      }
    },
    "issue": {
      "assignee": null,
      "assignees": [],
      "author_association": "COLLABORATOR",
      "body": null,
      "closed_at": null,
      "comments": 1,
      "comments_url": "https://api.github.com/repos/store2be/E2E/issues/18/comments",
      "created_at": "2019-11-14T14:20:59Z",
      "events_url": "https://api.github.com/repos/store2be/E2E/issues/18/events",
      "html_url": "https://github.com/store2be/E2E/pull/18",
      "id": 522889997,
      "labels": [],
      "labels_url": "https://api.github.com/repos/store2be/E2E/issues/18/labels{/name}",
      "locked": false,
      "milestone": null,
      "node_id": "MDExOlB1bGxSZXF1ZXN0MzQxMDAwMjc0",
      "number": 18,
      "pull_request": {
        "diff_url": "https://github.com/store2be/E2E/pull/18.diff",
        "html_url": "https://github.com/store2be/E2E/pull/18",
        "patch_url": "https://github.com/store2be/E2E/pull/18.patch",
        "url": "https://api.github.com/repos/store2be/E2E/pulls/18"
      },
      "repository_url": "https://api.github.com/repos/store2be/E2E",
      "state": "open",
      "title": "?? Change artifact upload from failure to always",
      "updated_at": "2019-11-14T14:21:14Z",
      "url": "https://api.github.com/repos/store2be/E2E/issues/18",
      "user": {
        "avatar_url": "https://avatars1.githubusercontent.com/u/4454052?v=4",
        "events_url": "https://api.github.com/users/peterfication/events{/privacy}",
        "followers_url": "https://api.github.com/users/peterfication/followers",
        "following_url": "https://api.github.com/users/peterfication/following{/other_user}",
        "gists_url": "https://api.github.com/users/peterfication/gists{/gist_id}",
        "gravatar_id": "",
        "html_url": "https://github.com/peterfication",
        "id": 4454052,
        "login": "peterfication",
        "node_id": "MDQ6VXNlcjQ0NTQwNTI=",
        "organizations_url": "https://api.github.com/users/peterfication/orgs",
        "received_events_url": "https://api.github.com/users/peterfication/received_events",
        "repos_url": "https://api.github.com/users/peterfication/repos",
        "site_admin": false,
        "starred_url": "https://api.github.com/users/peterfication/starred{/owner}{/repo}",
        "subscriptions_url": "https://api.github.com/users/peterfication/subscriptions",
        "type": "User",
        "url": "https://api.github.com/users/peterfication"
      }
    },
    "organization": {
      "avatar_url": "https://avatars1.githubusercontent.com/u/19347720?v=4",
      "description": "store2be is an online marketplace for short-term retail and promotion space.",
      "events_url": "https://api.github.com/orgs/store2be/events",
      "hooks_url": "https://api.github.com/orgs/store2be/hooks",
      "id": 19347720,
      "issues_url": "https://api.github.com/orgs/store2be/issues",
      "login": "store2be",
      "members_url": "https://api.github.com/orgs/store2be/members{/member}",
      "node_id": "MDEyOk9yZ2FuaXphdGlvbjE5MzQ3NzIw",
      "public_members_url": "https://api.github.com/orgs/store2be/public_members{/member}",
      "repos_url": "https://api.github.com/orgs/store2be/repos",
      "url": "https://api.github.com/orgs/store2be"
    },
    "repository": {
      "archive_url": "https://api.github.com/repos/store2be/E2E/{archive_format}{/ref}",
      "archived": false,
      "assignees_url": "https://api.github.com/repos/store2be/E2E/assignees{/user}",
      "blobs_url": "https://api.github.com/repos/store2be/E2E/git/blobs{/sha}",
      "branches_url": "https://api.github.com/repos/store2be/E2E/branches{/branch}",
      "clone_url": "https://github.com/store2be/E2E.git",
      "collaborators_url": "https://api.github.com/repos/store2be/E2E/collaborators{/collaborator}",
      "comments_url": "https://api.github.com/repos/store2be/E2E/comments{/number}",
      "commits_url": "https://api.github.com/repos/store2be/E2E/commits{/sha}",
      "compare_url": "https://api.github.com/repos/store2be/E2E/compare/{base}...{head}",
      "contents_url": "https://api.github.com/repos/store2be/E2E/contents/{+path}",
      "contributors_url": "https://api.github.com/repos/store2be/E2E/contributors",
      "created_at": "2019-08-27T07:33:54Z",
      "default_branch": "master",
      "deployments_url": "https://api.github.com/repos/store2be/E2E/deployments",
      "description": null,
      "disabled": false,
      "downloads_url": "https://api.github.com/repos/store2be/E2E/downloads",
      "events_url": "https://api.github.com/repos/store2be/E2E/events",
      "fork": false,
      "forks": 0,
      "forks_count": 0,
      "forks_url": "https://api.github.com/repos/store2be/E2E/forks",
      "full_name": "store2be/E2E",
      "git_commits_url": "https://api.github.com/repos/store2be/E2E/git/commits{/sha}",
      "git_refs_url": "https://api.github.com/repos/store2be/E2E/git/refs{/sha}",
      "git_tags_url": "https://api.github.com/repos/store2be/E2E/git/tags{/sha}",
      "git_url": "git://github.com/store2be/E2E.git",
      "has_downloads": true,
      "has_issues": true,
      "has_pages": false,
      "has_projects": true,
      "has_wiki": true,
      "homepage": null,
      "hooks_url": "https://api.github.com/repos/store2be/E2E/hooks",
      "html_url": "https://github.com/store2be/E2E",
      "id": 204646724,
      "issue_comment_url": "https://api.github.com/repos/store2be/E2E/issues/comments{/number}",
      "issue_events_url": "https://api.github.com/repos/store2be/E2E/issues/events{/number}",
      "issues_url": "https://api.github.com/repos/store2be/E2E/issues{/number}",
      "keys_url": "https://api.github.com/repos/store2be/E2E/keys{/key_id}",
      "labels_url": "https://api.github.com/repos/store2be/E2E/labels{/name}",
      "language": "TypeScript",
      "languages_url": "https://api.github.com/repos/store2be/E2E/languages",
      "license": null,
      "merges_url": "https://api.github.com/repos/store2be/E2E/merges",
      "milestones_url": "https://api.github.com/repos/store2be/E2E/milestones{/number}",
      "mirror_url": null,
      "name": "E2E",
      "node_id": "MDEwOlJlcG9zaXRvcnkyMDQ2NDY3MjQ=",
      "notifications_url": "https://api.github.com/repos/store2be/E2E/notifications{?since,all,participating}",
      "open_issues": 1,
      "open_issues_count": 1,
      "owner": {
        "avatar_url": "https://avatars1.githubusercontent.com/u/19347720?v=4",
        "events_url": "https://api.github.com/users/store2be/events{/privacy}",
        "followers_url": "https://api.github.com/users/store2be/followers",
        "following_url": "https://api.github.com/users/store2be/following{/other_user}",
        "gists_url": "https://api.github.com/users/store2be/gists{/gist_id}",
        "gravatar_id": "",
        "html_url": "https://github.com/store2be",
        "id": 19347720,
        "login": "store2be",
        "node_id": "MDEyOk9yZ2FuaXphdGlvbjE5MzQ3NzIw",
        "organizations_url": "https://api.github.com/users/store2be/orgs",
        "received_events_url": "https://api.github.com/users/store2be/received_events",
        "repos_url": "https://api.github.com/users/store2be/repos",
        "site_admin": false,
        "starred_url": "https://api.github.com/users/store2be/starred{/owner}{/repo}",
        "subscriptions_url": "https://api.github.com/users/store2be/subscriptions",
        "type": "Organization",
        "url": "https://api.github.com/users/store2be"
      },
      "private": true,
      "pulls_url": "https://api.github.com/repos/store2be/E2E/pulls{/number}",
      "pushed_at": "2019-11-14T14:21:00Z",
      "releases_url": "https://api.github.com/repos/store2be/E2E/releases{/id}",
      "size": 349,
      "ssh_url": "git@github.com:store2be/E2E.git",
      "stargazers_count": 1,
      "stargazers_url": "https://api.github.com/repos/store2be/E2E/stargazers",
      "statuses_url": "https://api.github.com/repos/store2be/E2E/statuses/{sha}",
      "subscribers_url": "https://api.github.com/repos/store2be/E2E/subscribers",
      "subscription_url": "https://api.github.com/repos/store2be/E2E/subscription",
      "svn_url": "https://github.com/store2be/E2E",
      "tags_url": "https://api.github.com/repos/store2be/E2E/tags",
      "teams_url": "https://api.github.com/repos/store2be/E2E/teams",
      "trees_url": "https://api.github.com/repos/store2be/E2E/git/trees{/sha}",
      "updated_at": "2019-11-14T14:19:50Z",
      "url": "https://api.github.com/repos/store2be/E2E",
      "watchers": 1,
      "watchers_count": 1
    },
    "sender": {
      "avatar_url": "https://avatars1.githubusercontent.com/u/4454052?v=4",
      "events_url": "https://api.github.com/users/peterfication/events{/privacy}",
      "followers_url": "https://api.github.com/users/peterfication/followers",
      "following_url": "https://api.github.com/users/peterfication/following{/other_user}",
      "gists_url": "https://api.github.com/users/peterfication/gists{/gist_id}",
      "gravatar_id": "",
      "html_url": "https://github.com/peterfication",
      "id": 4454052,
      "login": "peterfication",
      "node_id": "MDQ6VXNlcjQ0NTQwNTI=",
      "organizations_url": "https://api.github.com/users/peterfication/orgs",
      "received_events_url": "https://api.github.com/users/peterfication/received_events",
      "repos_url": "https://api.github.com/users/peterfication/repos",
      "site_admin": false,
      "starred_url": "https://api.github.com/users/peterfication/starred{/owner}{/repo}",
      "subscriptions_url": "https://api.github.com/users/peterfication/subscriptions",
      "type": "User",
      "url": "https://api.github.com/users/peterfication"
    }
}

